mypythonlib/__init__.py
mypythonlib/myfunctions.py
mypythonlib_lrdsssd-0.1.0.dist-info/METADATA
mypythonlib_lrdsssd-0.1.0.dist-info/WHEEL
mypythonlib_lrdsssd-0.1.0.dist-info/top_level.txt
mypythonlib_lrdsssd-0.1.0.dist-info/RECORD
